odoo9_addon_mail_optional_autofollow-9.0.1.0.0.99.dev8-py2.7-nspkg.pth
odoo9_addon_mail_optional_autofollow-9.0.1.0.0.99.dev8.dist-info/DESCRIPTION.rst
odoo9_addon_mail_optional_autofollow-9.0.1.0.0.99.dev8.dist-info/METADATA
odoo9_addon_mail_optional_autofollow-9.0.1.0.0.99.dev8.dist-info/RECORD
odoo9_addon_mail_optional_autofollow-9.0.1.0.0.99.dev8.dist-info/WHEEL
odoo9_addon_mail_optional_autofollow-9.0.1.0.0.99.dev8.dist-info/metadata.json
odoo9_addon_mail_optional_autofollow-9.0.1.0.0.99.dev8.dist-info/namespace_packages.txt
odoo9_addon_mail_optional_autofollow-9.0.1.0.0.99.dev8.dist-info/top_level.txt
odoo_addons/mail_optional_autofollow/README.rst
odoo_addons/mail_optional_autofollow/__init__.py
odoo_addons/mail_optional_autofollow/__openerp__.py
odoo_addons/mail_optional_autofollow/i18n/ca.po
odoo_addons/mail_optional_autofollow/i18n/de.po
odoo_addons/mail_optional_autofollow/i18n/es.po
odoo_addons/mail_optional_autofollow/i18n/es_CO.po
odoo_addons/mail_optional_autofollow/i18n/fr.po
odoo_addons/mail_optional_autofollow/i18n/hr.po
odoo_addons/mail_optional_autofollow/i18n/mail_optional_autofollow.pot
odoo_addons/mail_optional_autofollow/i18n/pt_BR.po
odoo_addons/mail_optional_autofollow/i18n/sl.po
odoo_addons/mail_optional_autofollow/static/description/autofollow.png
odoo_addons/mail_optional_autofollow/static/description/icon.png
odoo_addons/mail_optional_autofollow/tests/__init__.py
odoo_addons/mail_optional_autofollow/tests/test_mail_optional_autofollow.py
odoo_addons/mail_optional_autofollow/wizard/__init__.py
odoo_addons/mail_optional_autofollow/wizard/mail_compose_message.py
odoo_addons/mail_optional_autofollow/wizard/mail_compose_message_view.xml
